bigtrack/__init__.py
bigtrack/composite_track.py
bigtrack/core.py
bigtrack/genome.py
bigtrack/group.py
bigtrack/hub.py
bigtrack/hub_component.py
bigtrack/multiwig.py
bigtrack/sampled_track.py
bigtrack/settings.py
bigtrack/super_track.py
bigtrack/track.py
bigtrack/trackdb.py
bigtrack-0.2.dist-info/licenses/LICENSE
bigtrack-0.2.dist-info/METADATA
bigtrack-0.2.dist-info/WHEEL
bigtrack-0.2.dist-info/top_level.txt
bigtrack-0.2.dist-info/RECORD
