Metadata-Version: 2.4
Name: bigtrack
Version: 0.2
Summary: A lightweight Python package for creating UCSC Track Hubs with ease.
Author-email: Shilong Zhang <shilong.zhang@sjtu.edu.cn>
License: MIT
Keywords: UCSC,track hub,genomics,bioinformatics
Requires-Python: >=3.7
License-File: LICENSE
Dynamic: license-file
